buildbot_worker/VERSION
buildbot_worker/__init__.py
buildbot_worker/base.py
buildbot_worker/bot.py
buildbot_worker/compat.py
buildbot_worker/exceptions.py
buildbot_worker/interfaces.py
buildbot_worker/msgpack.py
buildbot_worker/null.py
buildbot_worker/pb.py
buildbot_worker/pbutil.py
buildbot_worker/runprocess.py
buildbot_worker/tunnel.py
buildbot_worker/commands/__init__.py
buildbot_worker/commands/base.py
buildbot_worker/commands/fs.py
buildbot_worker/commands/registry.py
buildbot_worker/commands/shell.py
buildbot_worker/commands/transfer.py
buildbot_worker/commands/utils.py
buildbot_worker/monkeypatches/__init__.py
buildbot_worker/scripts/__init__.py
buildbot_worker/scripts/base.py
buildbot_worker/scripts/create_worker.py
buildbot_worker/scripts/logwatcher.py
buildbot_worker/scripts/restart.py
buildbot_worker/scripts/runner.py
buildbot_worker/scripts/start.py
buildbot_worker/scripts/stop.py
buildbot_worker/scripts/windows_service.py
buildbot_worker/util/__init__.py
buildbot_worker/util/_hangcheck.py
buildbot_worker/util/_notifier.py
buildbot_worker/util/buffer_manager.py
buildbot_worker/util/deferwaiter.py
buildbot_worker/util/lineboundaries.py
buildbot_worker/util/twisted.py
buildbot_worker-4.3.0.dist-info/COPYING
buildbot_worker-4.3.0.dist-info/METADATA
buildbot_worker-4.3.0.dist-info/WHEEL
buildbot_worker-4.3.0.dist-info/entry_points.txt
buildbot_worker-4.3.0.dist-info/top_level.txt
buildbot_worker-4.3.0.dist-info/RECORD
